pyspinners.py
pyspinners-0.0.3.dist-info/LICENSE
pyspinners-0.0.3.dist-info/METADATA
pyspinners-0.0.3.dist-info/WHEEL
pyspinners-0.0.3.dist-info/top_level.txt
pyspinners-0.0.3.dist-info/RECORD
