Metadata-Version: 2.1
Name: pyspinners
Version: 0.0.3
Summary: CLI Progress Spinner collection
Home-page: https://github.com/tsimpiris/PySpinners
Author: Ioannis Tsimpiris
Project-URL: Repository, https://github.com/tsimpiris/PySpinners
Classifier: Programming Language :: Python :: 3
Classifier: License :: OSI Approved :: MIT License
Classifier: Operating System :: OS Independent
Requires-Python: >=3.6
License-File: LICENSE
